SegmentationEvaluationTools/SIKOverlapTools.py
SegmentationEvaluationTools/__init__.py
SegmentationEvaluationTools-0.0.9.dist-info/LICENSE.txt
SegmentationEvaluationTools-0.0.9.dist-info/METADATA
SegmentationEvaluationTools-0.0.9.dist-info/WHEEL
SegmentationEvaluationTools-0.0.9.dist-info/top_level.txt
SegmentationEvaluationTools-0.0.9.dist-info/RECORD
